randomlib/__init__.py
randomlib/setup.py
randomlib/datasets/__init__.py
randomlib/datasets/loadData.py
randomlib/hate/__init__.py
randomlib/hate/hate.py
randomlib/modelRepo/__init__.py
randomlib/modelRepo/mahaHate.py
randomlib/modelRepo/mahaNER.py
randomlib/modelRepo/mahaSentiment.py
randomlib/ner/__init__.py
randomlib/ner/ner.py
randomlib/preprocess/__init__.py
randomlib/preprocess/marathiStopwords.txt
randomlib/preprocess/preprocess.py
randomlib/sentiment/__init__.py
randomlib/sentiment/sentiment.py
randomlib/tokenizer/__init__.py
randomlib/tokenizer/tokenize.py
randomlib-0.13.dist-info/LICENSE.txt
randomlib-0.13.dist-info/METADATA
randomlib-0.13.dist-info/WHEEL
randomlib-0.13.dist-info/top_level.txt
randomlib-0.13.dist-info/RECORD
